MANIFEST.in
README.rst
lz4toolsCli
setup.py
lz4tools/__init__.py
lz4tools/__main__.py
lz4tools/lz4file.py
lz4tools/lz4tar.py
lz4tools.egg-info/PKG-INFO
lz4tools.egg-info/SOURCES.txt
lz4tools.egg-info/dependency_links.txt
lz4tools.egg-info/top_level.txt
src/lz4.c
src/lz4.h
src/lz4frame.c
src/lz4frame.h
src/lz4frame_static.h
src/lz4hc.c
src/lz4hc.h
src/python-lz4f.c
src/python-lz4f.h
src/xxhash.c
src/xxhash.h