Metadata-Version: 1.1
Name: lz4tools
Version: 1.3.1.2
Summary: LZ4Frame Bindings and tools for Python
Home-page: https://github.com/darkdragn/lz4file
Author: Christopher Jackson
Author-email: darkdragn.cj@gmail.com
License: BSD
Keywords: lz4,lz4frame,lz4file,lz4tar
Platform: UNKNOWN
Classifier: Development Status :: 5 - Production/Stable
Classifier: License :: OSI Approved :: BSD License
Classifier: Intended Audience :: Developers
Classifier: Programming Language :: C
Classifier: Programming Language :: Python
Classifier: Programming Language :: Python :: 2
Classifier: Programming Language :: Python :: 2.6
Classifier: Programming Language :: Python :: 2.7
Classifier: Programming Language :: Python :: 3
Classifier: Programming Language :: Python :: 3.2
Classifier: Programming Language :: Python :: 3.3
Classifier: Programming Language :: Python :: 3.4
